{
	"info": {
		"_postman_id": "dad12bf5-f3b9-456e-902d-ffc2470a3604",
		"name": "User",
		"schema": "https://schema.getpostman.com/json/collection/v2.1.0/collection.json",
		"_exporter_id": "37413959"
	},
	"item": [
		{
			"name": "GetUsers",
			"request": {
				"method": "GET",
				"header": [],
				"url": {
					"raw": "http://localhost:3000/adoptionSystem/v1/users",
					"protocol": "http",
					"host": [
						"localhost"
					],
					"port": "3000",
					"path": [
						"adoptionSystem",
						"v1",
						"users"
					]
				}
			},
			"response": []
		},
		{
			"name": "DeleteUser",
			"request": {
				"method": "DELETE",
				"header": [
					{
						"key": "x-token",
						"value": "eyJhbGciOiJIUzI1NiIsInR5cCI6IkpXVCJ9.eyJ1aWQiOiI2N2FhODA1ZjYzNTE5Zjg2MWM5ZGNhZTUiLCJpYXQiOjE3MzkyMjc2MTEsImV4cCI6MTczOTIzMTIxMX0.2c88sd20C_1bggbSafz86oXwVWbvXT_hyVoUpX4Qig8",
						"type": "text"
					}
				],
				"url": {
					"raw": "http://localhost:3000/adoptionSystem/v1/users/67aa814763519f861c9dcaeb",
					"protocol": "http",
					"host": [
						"localhost"
					],
					"port": "3000",
					"path": [
						"adoptionSystem",
						"v1",
						"users",
						"67aa814763519f861c9dcaeb"
					]
				}
			},
			"response": []
		},
		{
			"name": "SearchUser",
			"request": {
				"method": "GET",
				"header": [],
				"url": {
					"raw": "http://localhost:3000/adoptionSystem/v1/users/findUser/67a3e3ecfaf087b5b77375b2",
					"protocol": "http",
					"host": [
						"localhost"
					],
					"port": "3000",
					"path": [
						"adoptionSystem",
						"v1",
						"users",
						"findUser",
						"67a3e3ecfaf087b5b77375b2"
					]
				}
			},
			"response": []
		},
		{
			"name": "UpdateUser",
			"request": {
				"method": "PUT",
				"header": [],
				"body": {
					"mode": "raw",
					"raw": "{\r\n    \"name\": \"Saul\",\r\n    \"surname\": \"Donis\",\r\n    \"username\": \"sdonis\",\r\n    \"email\": \"sdonis@kinal.edu.gt\",\r\n    \"password\": \"22445566\",\r\n    \"profilePicture\": \" \",\r\n    \"phone\": \"88994455\",\r\n    \"role\": \"USER_ROLE\"\r\n}",
					"options": {
						"raw": {
							"language": "json"
						}
					}
				},
				"url": {
					"raw": "http://localhost:3000/adoptionSystem/v1/users/67a3bac089eece4701a351c4",
					"protocol": "http",
					"host": [
						"localhost"
					],
					"port": "3000",
					"path": [
						"adoptionSystem",
						"v1",
						"users",
						"67a3bac089eece4701a351c4"
					]
				}
			},
			"response": []
		},
		{
			"name": "UpdatePassword",
			"request": {
				"method": "PUT",
				"header": [],
				"body": {
					"mode": "raw",
					"raw": "{\r\n    \"password\": \"33332222\"\r\n}",
					"options": {
						"raw": {
							"language": "json"
						}
					}
				},
				"url": {
					"raw": "http://localhost:3000/adoptionSystem/v1/users/newpassword/67abc6ecea9416d17d436347",
					"protocol": "http",
					"host": [
						"localhost"
					],
					"port": "3000",
					"path": [
						"adoptionSystem",
						"v1",
						"users",
						"newpassword",
						"67abc6ecea9416d17d436347"
					]
				}
			},
			"response": []
		}
	]
}